llm_wrapper/__init__.py
llm_wrapper/config.py
llm_wrapper/llm_wrapper.py
llm_wrapper_yl-0.1.3.dist-info/METADATA
llm_wrapper_yl-0.1.3.dist-info/WHEEL
llm_wrapper_yl-0.1.3.dist-info/licenses/LICENSE
llm_wrapper_yl-0.1.3.dist-info/RECORD
