Metadata-Version: 2.4
Name: llm-wrapper-yl
Version: 0.1.3
Summary: A flexible wrapper for LLM providers with caching, async support, and cost tracking
Project-URL: Homepage, https://github.com/yoonholee/llm-wrapper
Project-URL: Repository, https://github.com/yoonholee/llm-wrapper.git
Author-email: Yoonho Lee <yoonho@stanford.edu>
License: MIT
License-File: LICENSE
Requires-Python: >=3.11
Requires-Dist: diskcache>=5.6.3
Requires-Dist: nest-asyncio>=1.6.0
Requires-Dist: openai>=1.65.1
Requires-Dist: requests>=2.31.0
Requires-Dist: tenacity>=8.5.0
Requires-Dist: together>=1.5.4
Requires-Dist: tqdm>=4.67.1
Provides-Extra: test
Requires-Dist: pytest>=8.3.5; extra == 'test'
